owopkg/__init__.py
owopkg/__main__.py
owopkg/build.py
owopkg/creates.py
owopkg/deploy.py
owopkg/lib.py
owopkg/mybwb.py
owopkg-0.0.2.dist-info/LICENSE
owopkg-0.0.2.dist-info/METADATA
owopkg-0.0.2.dist-info/WHEEL
owopkg-0.0.2.dist-info/top_level.txt
owopkg-0.0.2.dist-info/RECORD
